poisson/__init__.py
poisson/errors.py
poisson/poisson.py
poisson/utils.py
poissongeometry-1.0.2.dist-info/LICENSE.md
poissongeometry-1.0.2.dist-info/METADATA
poissongeometry-1.0.2.dist-info/WHEEL
poissongeometry-1.0.2.dist-info/top_level.txt
poissongeometry-1.0.2.dist-info/RECORD
