Metadata-Version: 2.1
Name: poissongeometry
Version: 1.0.2
Summary: A Python module for (local) Poisson-Nijenhuis calculus on Poisson manifolds
Home-page: https://github.com/appliedgeometry/poisson_geometry
Author: Miguel Evangelista-Alvarado, José C. Ruíz Pantaleón, Pablo Suárez-Serrato
Author-email: miguel.eva.alv@gmail.com, jcpanta@im.unam.mx, pablo@im.unam.mx
License: MIT
Platform: UNKNOWN
Classifier: Development Status :: 5 - Production/Stable
Classifier: Programming Language :: Python :: 3 :: Only
Classifier: License :: OSI Approved :: MIT License
Classifier: Operating System :: OS Independent
Classifier: Topic :: Scientific/Engineering :: Mathematics
Classifier: Intended Audience :: Science/Research
Requires-Python: >=3.6
License-File: LICENSE.md
Requires-Dist: sympy
Requires-Dist: numpy
